Metadata-Version: 2.1
Name: flowmeta
Version: 0.1.6
Summary: Integrated metagenomic workflow orchestration
Author-email: Dongqiang Zeng <interlaken@smu.edu.cn>
License: Proprietary
Requires-Python: >=3.8
License-File: LICENSE
Requires-Dist: numpy>=1.21
Requires-Dist: pandas>=1.5
